dictoat/__init__.py
dictoat/dictoat.py
dictoat-1.0.1.dist-info/LICENSE
dictoat-1.0.1.dist-info/METADATA
dictoat-1.0.1.dist-info/WHEEL
dictoat-1.0.1.dist-info/top_level.txt
dictoat-1.0.1.dist-info/RECORD
