Metadata-Version: 2.1
Name: dictoat
Version: 1.0.1
Summary: Convert a dict into an object to access items faster.
Home-page: https://github.com/niCodeLine/dictoat
Author: Nico Spok
Author-email: nicospok@hotmail.com
License: MIT
Classifier: Programming Language :: Python :: 3
Classifier: License :: OSI Approved :: MIT License
Classifier: Operating System :: OS Independent
Requires-Python: >=3.6
License-File: LICENSE
